PyTermStylePlus.py
pytermstyleplus-0.1.1.dist-info/licenses/LICENSE
pytermstyleplus-0.1.1.dist-info/METADATA
pytermstyleplus-0.1.1.dist-info/WHEEL
pytermstyleplus-0.1.1.dist-info/top_level.txt
pytermstyleplus-0.1.1.dist-info/RECORD
