Metadata-Version: 2.4
Name: PyTermStylePlus
Version: 0.1.1
Summary: An elegant Python library for terminal text styling with themes.
Home-page: https://github.com/Mohammedcha/PyTermStylePlus
Author: Mohammedcha
Author-email: contact@mohammedcha.com
Classifier: Programming Language :: Python :: 3
Classifier: License :: OSI Approved :: MIT License
Classifier: Operating System :: OS Independent
Classifier: Environment :: Console
Classifier: Intended Audience :: Developers
Classifier: Topic :: Software Development :: Libraries :: Python Modules
Classifier: Topic :: Terminals
Classifier: Development Status :: 3 - Alpha
Requires-Python: >=3.6
License-File: LICENSE
Dynamic: author
Dynamic: author-email
Dynamic: classifier
Dynamic: description
Dynamic: description-content-type
Dynamic: home-page
Dynamic: license-file
Dynamic: requires-python
Dynamic: summary
